pyfilerver/__init__.py
pyfilerver/main.py
pyfilerver-0.0.10.dist-info/LICENSE
pyfilerver-0.0.10.dist-info/METADATA
pyfilerver-0.0.10.dist-info/WHEEL
pyfilerver-0.0.10.dist-info/entry_points.txt
pyfilerver-0.0.10.dist-info/RECORD
