Metadata-Version: 2.1
Name: pyfilerver
Version: 0.0.10
Summary: Python Http File Server: Added file upload function to `http.server`
Home-page: https://github.com/IanVzs/pyfilerver
License: MIT
Author: ianvzs
Author-email: ianvzs@outlook.com
Requires-Python: >=3.7,<=3.12
Classifier: License :: OSI Approved :: MIT License
Classifier: Programming Language :: Python :: 3
Classifier: Programming Language :: Python :: 3.7
Classifier: Programming Language :: Python :: 3.8
Classifier: Programming Language :: Python :: 3.9
Classifier: Programming Language :: Python :: 3.10
Classifier: Programming Language :: Python :: 3.11
Project-URL: Repository, https://github.com/IanVzs/pyfilerver
